catnado/__init__.py
catnado/handlers/__init__.py
catnado/handlers/csrf_protected_handler.py
catnado/handlers/service_api_handler.py
catnado/handlers/simple_public_handler.py
catnado/handlers/static_page_handler.py
catnado/properties/__init__.py
catnado/properties/array_property.py
catnado/properties/choice_property.py
catnado/properties/compressed_property.py
catnado/properties/decimal_property.py
catnado/properties/derived_property.py
catnado/properties/domain_property.py
catnado/properties/immutabe_property.py
catnado/properties/json_property.py
catnado/properties/key_property.py
catnado/properties/pickle_property.py
catnado/properties/set_property.py
catnado/properties/transform_property.py
catnado/properties/translatable_property.py
catnado/testing/__init__.py
catnado/testing/app.py
catnado/testing/testcase.py
catnado/testing/urlfetch.py
catnado/unique_property_record/__init__.py
catnado/unique_property_record/test_unique_property_record.py
catnado/utils/__init__.py
catnado/utils/api.py
catnado/utils/csrf.py
catnado/utils/environment.py
catnado/utils/jinja.py
catnado/utils/validators.py
catnado/versionedmodel/__init__.py
catnado/versionedmodel/test_versionedmodel.py
gae_catnado-0.0.1.dev33.dist-info/LICENSE.txt
gae_catnado-0.0.1.dev33.dist-info/METADATA
gae_catnado-0.0.1.dev33.dist-info/RECORD
gae_catnado-0.0.1.dev33.dist-info/WHEEL
gae_catnado-0.0.1.dev33.dist-info/top_level.txt
