Metadata-Version: 2.1
Name: gae-catnado
Version: 0.0.1.dev33
Summary: Google App Engine datastore properties and helpers
Home-page: https://github.com/tylertrussell/gae-catnado
Author: Tyler Trussell
Author-email: tigertrussell+pip@gmail.com
License: UNKNOWN
Keywords: google app engine helpers datastore properties
Platform: UNKNOWN
Requires-Dist: jsonschema
